e197f81d520c29e4d5d0__mypyc.cpython-312-x86_64-linux-gnu.so
cumulonimbus_models/operation_submissions.cpython-312-x86_64-linux-gnu.so
cumulonimbus_models/operation_submissions.py
cumulonimbus_models/api.py
cumulonimbus_models/agent.cpython-312-x86_64-linux-gnu.so
cumulonimbus_models/api.cpython-312-x86_64-linux-gnu.so
cumulonimbus_models/constants.cpython-312-x86_64-linux-gnu.so
cumulonimbus_models/settings.cpython-312-x86_64-linux-gnu.so
cumulonimbus_models/operations.cpython-312-x86_64-linux-gnu.so
cumulonimbus_models/py.typed
cumulonimbus_models/settings.py
cumulonimbus_models/constants.py
cumulonimbus_models/__init__.py
cumulonimbus_models/installation_types.cpython-312-x86_64-linux-gnu.so
cumulonimbus_models/system.py
cumulonimbus_models/agent.py
cumulonimbus_models/installation_types.py
cumulonimbus_models/__init__.cpython-312-x86_64-linux-gnu.so
cumulonimbus_models/system.cpython-312-x86_64-linux-gnu.so
cumulonimbus_models/operations.py
cumulonimbus_models-0.0.0.dist-info/RECORD
cumulonimbus_models-0.0.0.dist-info/WHEEL
cumulonimbus_models-0.0.0.dist-info/LICENSE
cumulonimbus_models-0.0.0.dist-info/top_level.txt
cumulonimbus_models-0.0.0.dist-info/METADATA
