Metadata-Version: 2.1
Name: cumulonimbus-models
Version: 0.0.0
Author-email: Guy Wilson <guywilsonjr@gmail.com>
Maintainer-email: Guy Wilson <guywilsonjr@gmail.com>
Project-URL: Homepage, https://github.com/guywilsonjr/cdk-simple-constructs-python
Project-URL: Repository, https://github.com/guywilsonjr/cdk-simple-constructs-python
Classifier: Development Status :: 3 - Alpha
Classifier: Intended Audience :: Developers
Classifier: Topic :: Software Development :: Build Tools
Classifier: License :: OSI Approved :: Apple Public Source License
Classifier: Programming Language :: Python :: 3
Classifier: Programming Language :: Python :: 3.10
Classifier: Programming Language :: Python :: 3.11
Classifier: Programming Language :: Python :: 3.12
Requires-Python: <3.13,>=3.12
License-File: LICENSE
Requires-Dist: annotated-types ==0.7.0
Requires-Dist: pydantic ==2.8.2
Requires-Dist: pydantic-core ==2.20.1
Requires-Dist: pydantic-settings ==2.4.0
Requires-Dist: python-dotenv ==1.0.1
Requires-Dist: typing-extensions ==4.12.2
